README.md
setup.py
XPRESStools.egg-info/PKG-INFO
XPRESStools.egg-info/SOURCES.txt
XPRESStools.egg-info/dependency_links.txt
XPRESStools.egg-info/not-zip-safe
XPRESStools.egg-info/requires.txt
XPRESStools.egg-info/top_level.txt
xpresstools/__init__.py
xpresstools/analyze.py
xpresstools/collapser.py
xpresstools/fetch.py
xpresstools/format.py
xpresstools/interactive.py
xpresstools/normalize.py
xpresstools/utils.py
xpresstools/utils_analyze.py