Metadata-Version: 2.1
Name: XPRESStools
Version: 0.0.4b0
Summary: A toolkit for navigating and analyzing gene expression datasets
Home-page: https://github.com/XPRESSyourself/XPRESStools
Author: Jordan Berg
Author-email: jordan.berg@biochem.utah.edu
License: GPL-3.0
Platform: UNKNOWN
Classifier: Development Status :: 4 - Beta
Classifier: Intended Audience :: Science/Research
Classifier: Topic :: Scientific/Engineering :: Bio-Informatics
